HISTORY.rst
LICENSE.txt
MANIFEST.in
README.rst
setup.py
emencia/__init__.py
emencia.django.countries.egg-info/PKG-INFO
emencia.django.countries.egg-info/SOURCES.txt
emencia.django.countries.egg-info/dependency_links.txt
emencia.django.countries.egg-info/namespace_packages.txt
emencia.django.countries.egg-info/not-zip-safe
emencia.django.countries.egg-info/requires.txt
emencia.django.countries.egg-info/top_level.txt
emencia/django/__init__.py
emencia/django/countries/__init__.py
emencia/django/countries/admin.py
emencia/django/countries/context_processors.py
emencia/django/countries/managers.py
emencia/django/countries/models.py
emencia/django/countries/tests.py
emencia/django/countries/testsettings.py
emencia/django/countries/fixtures/initial_data.xml
emencia/django/countries/locale/fr/LC_MESSAGES/django.mo
emencia/django/countries/locale/fr/LC_MESSAGES/django.po
emencia/django/countries/migrations/0001_initial.py
emencia/django/countries/migrations/0002_auto_load_initial_data.py
emencia/django/countries/migrations/__init__.py
emencia/django/countries/templatetags/__init__.py
emencia/django/countries/templatetags/countries_tags.py