Metadata-Version: 1.1
Name: emencia.django.countries
Version: 0.2.2
Summary: List of manageable countries for your Django projects
Home-page: https://github.com/emencia/emencia-django-countries
Author: Fantomas42
Author-email: support@emencia.com
License: BSD License
Keywords: django,countries
Platform: UNKNOWN
Classifier: Programming Language :: Python
Classifier: License :: OSI Approved :: BSD License
Classifier: Operating System :: OS Independent
Classifier: Development Status :: 5 - Production/Stable
Classifier: Environment :: Web Environment
Classifier: Framework :: Django
Classifier: Framework :: Django :: 1.4
Classifier: Framework :: Django :: 1.5
Classifier: Framework :: Django :: 1.6
Classifier: Framework :: Django :: 1.7
Classifier: Framework :: Django :: 1.8
Classifier: Intended Audience :: Developers
Classifier: Topic :: Internet :: WWW/HTTP
Classifier: Topic :: Software Development :: Libraries :: Python Modules
